LICENSE.txt
evo_package_firebase/__init__.py
evo_package_firebase/automation/api.yaml
evo_package_firebase/automation/entity.yaml
evo_package_firebase/control/CFirebaseApi.py
evo_package_firebase/control/__init__.py
evo_package_firebase/entity/EFirebaseAdmin.py
evo_package_firebase/entity/EFirebaseMap.py
evo_package_firebase/entity/__init__.py
evo_package_firebase/utility/UFirebaseApi.py
evo_package_firebase/utility/__init__.py
evo_package_firebase-2024.10.211841.dist-info/LICENSE.txt
evo_package_firebase-2024.10.211841.dist-info/METADATA
evo_package_firebase-2024.10.211841.dist-info/WHEEL
evo_package_firebase-2024.10.211841.dist-info/RECORD
