Metadata-Version: 2.1
Name: evo-package-firebase
Version: 2024.10.211841
Summary: evo-package-firebase python
License: CC BY-NC-ND 4.0
Author: cyborg-ai-git
Author-email: 129898917+cyborg-ai-git@users.noreply.github.com
Requires-Python: >=3.10,<4.0
Classifier: License :: Other/Proprietary License
Classifier: Programming Language :: Python :: 3
Classifier: Programming Language :: Python :: 3.10
Classifier: Programming Language :: Python :: 3.11
Classifier: Programming Language :: Python :: 3.12
Requires-Dist: evo-framework
Requires-Dist: firebase_admin (>=6.5.0,<7.0.0)
Requires-Dist: google-auth (>=2.27.0,<3.0.0)
Requires-Dist: google-cloud-firestore (>=2.16.0,<3.0.0)
Requires-Dist: google-cloud-storage (>=2.17.0,<3.0.0)
